gitlab_export/__init__.py
gitlab_export/config.py
gitlab_export/gitlab.py
gitlab_project_export-0.1.2.data/scripts/gitlab-project-export.py
gitlab_project_export-0.1.2.data/scripts/gitlab-project-import.py
gitlab_project_export-0.1.2.dist-info/LICENSE
gitlab_project_export-0.1.2.dist-info/METADATA
gitlab_project_export-0.1.2.dist-info/WHEEL
gitlab_project_export-0.1.2.dist-info/top_level.txt
gitlab_project_export-0.1.2.dist-info/RECORD
