Metadata-Version: 2.1
Name: gitlab-project-export
Version: 0.1.2
Summary: Simple python project for exporting gitlab projects with Export Project feature in GitLab API.
Home-page: https://github.com/rvojcik/gitlab-project-export
Author: Robert Vojcik
Author-email: robert@vojcik.net
License: UNKNOWN
Download-URL: https://github.com/rvojcik/gitlab-project-export/archive/master.tar.gz
Keywords: gitlab-backup,gitlab-export,export,gitlab,backup
Platform: UNKNOWN
Classifier: Development Status :: 4 - Beta
Classifier: License :: OSI Approved :: GNU General Public License v3 (GPLv3)
Classifier: Programming Language :: Python
Classifier: Programming Language :: Python :: 3
License-File: LICENSE
Requires-Dist: pyyaml
Requires-Dist: requests
